[{"image": "1616_0_21530.png", "annotations": [{"label": "worm", "coordinates": {"x": 533.8023255813954, "y": 274.90697674418607, "width": 25.0, "height": 32.0}}, {"label": "worm", "coordinates": {"x": 506.8023255813954, "y": 484.40697674418607, "width": 21.000000000000057, "height": 29.0}}, {"label": "dynamite", "coordinates": {"x": 522.3023255813954, "y": 479.90697674418607, "width": 12.0, "height": 22.0}}, {"label": "worm", "coordinates": {"x": 592.3023255813954, "y": 472.90697674418607, "width": 24.0, "height": 32.0}}, {"label": "mine", "coordinates": {"x": 272.30232558139534, "y": 429.90697674418607, "width": 16.0, "height": 16.0}}, {"label": "worm", "coordinates": {"x": 265.80232558139534, "y": 585.4069767441861, "width": 25.0, "height": 33.0}}, {"label": "worm", "coordinates": {"x": 126.30232558139534, "y": 453.90697674418607, "width": 27.999999999999986, "height": 30.0}}, {"label": "worm", "coordinates": {"x": 147.80232558139534, "y": 341.90697674418607, "width": 25.0, "height": 32.0}}, {"label": "worm", "coordinates": {"x": 345.80232558139534, "y": 453.40697674418607, "width": 29.0, "height": 37.0}}, {"label": "worm", "coordinates": {"x": 697.8023255813954, "y": 304.40697674418607, "width": 25.0, "height": 35.0}}, {"label": "worm", "coordinates": {"x": 768.3023255813954, "y": 307.40697674418607, "width": 26.0, "height": 31.0}}, {"label": "barrel", "coordinates": {"x": 562.8023255813954, "y": 613.4069767441861, "width": 37.0, "height": 43.0}}, {"label": "worm", "coordinates": {"x": 426.30232558139534, "y": 482.40697674418607, "width": 26.0, "height": 33.0}}, {"label": "barrel", "coordinates": {"x": 73.30232558139535, "y": 302.40697674418607, "width": 32.0, "height": 41.0}}, {"label": "mine", "coordinates": {"x": 615.3023255813954, "y": 378.90697674418607, "width": 16.0, "height": 14.0}}]}]