[{"image": "3156_0_14068.png", "annotations": [{"label": "worm", "coordinates": {"x": 424.26108374384245, "y": 447.3251231527094, "width": 38.0, "height": 16.0}}, {"label": "dynamite", "coordinates": {"x": 428.26108374384245, "y": 436.8251231527094, "width": 14.0, "height": 23.0}}, {"label": "worm", "coordinates": {"x": 430.26108374384245, "y": 455.3251231527094, "width": 18.0, "height": 30.0}}, {"label": "worm", "coordinates": {"x": 141.26108374384242, "y": 556.8251231527095, "width": 24.0, "height": 29.0}}, {"label": "worm", "coordinates": {"x": 151.76108374384242, "y": 541.3251231527095, "width": 17.0, "height": 22.0}}, {"label": "worm", "coordinates": {"x": 152.76108374384242, "y": 240.3251231527094, "width": 21.0, "height": 31.99999999999997}}, {"label": "worm", "coordinates": {"x": 790.6305418719212, "y": 448.8251231527094, "width": 18.73891625615761, "height": 29.0}}, {"label": "worm", "coordinates": {"x": 783.7610837438424, "y": 100.82512315270942, "width": 21.0, "height": 29.0}}]}]