[{"image": "701_1_1791.png", "annotations": [{"label": "worm", "coordinates": {"x": 372.30232558139534, "y": 339.90697674418607, "width": 20.0, "height": 40.0}}, {"label": "dynamite", "coordinates": {"x": 535.3023255813954, "y": 317.40697674418607, "width": 14.0, "height": 25.0}}, {"label": "worm", "coordinates": {"x": 535.8023255813954, "y": 331.40697674418607, "width": 23.0, "height": 31.0}}, {"label": "worm", "coordinates": {"x": 547.3023255813954, "y": 592.9069767441861, "width": 20.0, "height": 34.0}}, {"label": "worm", "coordinates": {"x": 439.30232558139534, "y": 548.4069767441861, "width": 22.0, "height": 33.0}}, {"label": "worm", "coordinates": {"x": 290.30232558139534, "y": 397.40697674418607, "width": 26.0, "height": 31.0}}, {"label": "mine", "coordinates": {"x": 22.80232558139535, "y": 329.40697674418607, "width": 17.0, "height": 13.0}}, {"label": "mine", "coordinates": {"x": 129.80232558139534, "y": 176.90697674418604, "width": 18.999999999999986, "height": 12.0}}, {"label": "barrel", "coordinates": {"x": 6.151162790697675, "y": 114.40697674418604, "width": 12.30232558139535, "height": 39.0}}]}]