[{"image": "9_1_7901.png", "annotations": [{"label": "worm", "coordinates": {"x": 255.0, "y": 179.0, "width": 25.588241577148438, "height": 31.67657470703125}}, {"label": "worm", "coordinates": {"x": 201.0, "y": 317.0, "width": 23.848236083984375, "height": 32.06201171875}}, {"label": "worm", "coordinates": {"x": 656.0, "y": 535.0, "width": 24.4161376953125, "height": 31.96484375}}, {"label": "dynamite", "coordinates": {"x": 200.0, "y": 300.0, "width": 15.85504150390625, "height": 25.0262451171875}}, {"label": "barrel", "coordinates": {"x": 109.0, "y": 231.0, "width": 37.28208923339844, "height": 37.555755615234375}}, {"label": "barrel", "coordinates": {"x": 384.0, "y": 78.0, "width": 38.4320068359375, "height": 39.02402877807617}}]}]