[{"image": "9_1_15032.png", "annotations": [{"label": "worm", "coordinates": {"x": 632.0, "y": 535.0, "width": 24.207275390625, "height": 32.8089599609375}}, {"label": "worm", "coordinates": {"x": 177.0, "y": 316.0, "width": 23.79205322265625, "height": 34.32568359375}}, {"label": "worm", "coordinates": {"x": 199.0, "y": 191.0, "width": 23.611236572265625, "height": 30.6973876953125}}, {"label": "dynamite", "coordinates": {"x": 198.0, "y": 189.0, "width": 13.468902587890625, "height": 25.69976806640625}}, {"label": "barrel", "coordinates": {"x": 360.0, "y": 78.0, "width": 37.1339111328125, "height": 42.6973762512207}}, {"label": "barrel", "coordinates": {"x": 86.0, "y": 231.0, "width": 34.962005615234375, "height": 39.89471435546875}}]}]