[{"image": "hd_1086_0.png", "annotations": [{"label": "worm", "coordinates": {"x": 1202.0, "y": 276.0, "width": 25.012451171875, "height": 30.7021484375}}, {"label": "worm", "coordinates": {"x": 728.0, "y": 647.0, "width": 25.1328125, "height": 33.3553466796875}}, {"label": "worm", "coordinates": {"x": 1339.0, "y": 524.0, "width": 25.2117919921875, "height": 34.766265869140625}}, {"label": "worm", "coordinates": {"x": 215.0, "y": 233.0, "width": 26.304611206054688, "height": 37.290924072265625}}, {"label": "worm", "coordinates": {"x": 1602.0, "y": 433.0, "width": 25.87890625, "height": 34.529876708984375}}, {"label": "worm", "coordinates": {"x": 299.0, "y": 367.0, "width": 27.1556396484375, "height": 32.07244873046875}}, {"label": "worm", "coordinates": {"x": 1154.0, "y": 667.0, "width": 24.3001708984375, "height": 35.4605712890625}}, {"label": "worm", "coordinates": {"x": 624.0, "y": 446.0, "width": 28.44696044921875, "height": 32.34539794921875}}, {"label": "worm", "coordinates": {"x": 1269.0, "y": 584.0, "width": 26.438720703125, "height": 34.58453369140625}}, {"label": "worm", "coordinates": {"x": 867.0, "y": 322.0, "width": 27.53167724609375, "height": 34.40167236328125}}, {"label": "mine", "coordinates": {"x": 184.0, "y": 502.0, "width": 19.455093383789062, "height": 19.476165771484375}}, {"label": "mine", "coordinates": {"x": 516.0, "y": 372.0, "width": 20.062744140625, "height": 18.9285888671875}}, {"label": "worm", "coordinates": {"x": 1731.0, "y": 733.0, "width": 24.7435302734375, "height": 29.931884765625}}, {"label": "barrel", "coordinates": {"x": 947.0, "y": 668.0, "width": 36.57098388671875, "height": 45.51263427734375}}, {"label": "barrel", "coordinates": {"x": 220.0, "y": 375.0, "width": 35.79241943359375, "height": 44.2152099609375}}, {"label": "worm", "coordinates": {"x": 518.0, "y": 670.0, "width": 22.863037109375, "height": 37.20904541015625}}, {"label": "worm", "coordinates": {"x": 1669.0, "y": 480.0, "width": 22.188720703125, "height": 34.820953369140625}}, {"label": "mine", "coordinates": {"x": 1624.0, "y": 684.0, "width": 24.8514404296875, "height": 20.51251220703125}}, {"label": "worm", "coordinates": {"x": 327.0, "y": 682.0, "width": 21.712249755859375, "height": 35.18994140625}}, {"label": "barrel", "coordinates": {"x": 1056.0, "y": 208.0, "width": 36.3939208984375, "height": 45.36888122558594}}, {"label": "worm", "coordinates": {"x": 1433.0, "y": 520.0, "width": 22.886474609375, "height": 36.94403076171875}}, {"label": "dynamite", "coordinates": {"x": 1667.0, "y": 466.0, "width": 18.0135498046875, "height": 25.872283935546875}}, {"label": "mine", "coordinates": {"x": 245.7521367521366, "y": 688.1196581196581, "width": 16.0, "height": 16.0}}]}]