[{"image": "hd_102_1.png", "annotations": [{"coordinates": {"x": 780, "y": 732, "height": 34.72869873046875, "width": 26.81536865234375}, "label": "worm"}, {"coordinates": {"x": 1435, "y": 511, "height": 34.940338134765625, "width": 24.948486328125}, "label": "worm"}, {"coordinates": {"x": 900, "y": 591, "height": 31.8482666015625, "width": 27.2578125}, "label": "worm"}, {"coordinates": {"x": 612, "y": 599, "height": 37.53802490234375, "width": 24.7027587890625}, "label": "worm"}, {"coordinates": {"x": 991, "y": 736, "height": 32.5709228515625, "width": 25.49755859375}, "label": "worm"}, {"coordinates": {"x": 1168, "y": 537, "height": 34.96734619140625, "width": 25.493896484375}, "label": "worm"}, {"coordinates": {"x": 27, "y": 442, "height": 21.55780029296875, "width": 17.771129608154297}, "label": "mine"}, {"coordinates": {"x": 1060, "y": 894, "height": 38.4398193359375, "width": 35.9832763671875}, "label": "barrel"}, {"coordinates": {"x": 974, "y": 532, "height": 26.241943359375, "width": 18.02337646484375}, "label": "dynamite"}, {"coordinates": {"x": 959, "y": 542, "height": 39.70458984375, "width": 20.6031494140625}, "label": "worm"}, {"coordinates": {"x": 1413, "y": 982, "height": 38.92828369140625, "width": 24.9437255859375}, "label": "worm"}]}]