[{"image": "hd_1093_1.png", "annotations": [{"label": "worm", "coordinates": {"x": 1327.0, "y": 826.0, "width": 24.736083984375, "height": 33.78704833984375}}, {"label": "worm", "coordinates": {"x": 1073.0, "y": 428.0, "width": 27.09130859375, "height": 31.867767333984375}}, {"label": "worm", "coordinates": {"x": 802.0, "y": 820.0, "width": 27.26776123046875, "height": 31.00689697265625}}, {"label": "worm", "coordinates": {"x": 1213.0, "y": 818.0, "width": 27.087890625, "height": 34.21051025390625}}, {"label": "worm", "coordinates": {"x": 1305.0, "y": 441.0, "width": 25.0135498046875, "height": 29.328338623046875}}, {"label": "worm", "coordinates": {"x": 531.0, "y": 606.0, "width": 24.6246337890625, "height": 31.113037109375}}, {"label": "worm", "coordinates": {"x": 693.0, "y": 565.0, "width": 24.729736328125, "height": 29.95379638671875}}, {"label": "worm", "coordinates": {"x": 1369.0, "y": 744.0, "width": 22.7310791015625, "height": 30.27532958984375}}, {"label": "worm", "coordinates": {"x": 721.0, "y": 715.0, "width": 27.69158935546875, "height": 31.38653564453125}}, {"label": "worm", "coordinates": {"x": 424.0, "y": 854.0, "width": 24.69964599609375, "height": 33.16754150390625}}, {"label": "worm", "coordinates": {"x": 816.0, "y": 419.0, "width": 25.690673828125, "height": 28.9168701171875}}, {"label": "mine", "coordinates": {"x": 1828.0, "y": 865.0, "width": 21.6573486328125, "height": 16.6844482421875}}, {"label": "mine", "coordinates": {"x": 937.0, "y": 722.0, "width": 18.59747314453125, "height": 17.6510009765625}}, {"label": "worm", "coordinates": {"x": 1255.0, "y": 688.0, "width": 23.9669189453125, "height": 31.6705322265625}}, {"label": "mine", "coordinates": {"x": 335.0, "y": 391.0, "width": 19.917236328125, "height": 18.25225830078125}}, {"label": "mine", "coordinates": {"x": 254.0, "y": 448.0, "width": 19.411834716796875, "height": 17.215911865234375}}, {"label": "barrel", "coordinates": {"x": 1362.0, "y": 821.0, "width": 37.5150146484375, "height": 41.2877197265625}}, {"label": "barrel", "coordinates": {"x": 1202.0, "y": 341.0, "width": 34.892822265625, "height": 41.387969970703125}}, {"label": "barrel", "coordinates": {"x": 1391.0, "y": 312.0, "width": 34.594970703125, "height": 40.554595947265625}}, {"label": "dynamite", "coordinates": {"x": 1360.2521367521365, "y": 751.1196581196581, "width": 15.0, "height": 24.0}}, {"label": "worm", "coordinates": {"x": 858.7521367521366, "y": 364.1196581196581, "width": 24.0, "height": 32.0}}]}]