[{"image": "minehighres_6237.png", "annotations": [{"label": "barrel", "coordinates": {"x": 1228.0, "y": 497.0, "width": 31.728759765625, "height": 45.067169189453125}}, {"label": "barrel", "coordinates": {"x": 1252.0, "y": 746.0, "width": 30.8779296875, "height": 43.6959228515625}}, {"label": "barrel", "coordinates": {"x": 1090.0, "y": 416.0, "width": 32.923583984375, "height": 46.0823974609375}}, {"label": "barrel", "coordinates": {"x": 388.0, "y": 720.0, "width": 33.57623291015625, "height": 44.5814208984375}}, {"label": "barrel", "coordinates": {"x": 847.0, "y": 688.0, "width": 32.859619140625, "height": 44.45758056640625}}, {"label": "barrel", "coordinates": {"x": 1333.0, "y": 379.0, "width": 32.9029541015625, "height": 45.525054931640625}}, {"label": "barrel", "coordinates": {"x": 739.0, "y": 272.0, "width": 32.7740478515625, "height": 45.64964294433594}}, {"label": "barrel", "coordinates": {"x": 1575.0, "y": 439.0, "width": 32.976806640625, "height": 41.514801025390625}}, {"label": "barrel", "coordinates": {"x": 874.0, "y": 225.0, "width": 32.98419189453125, "height": 44.68064880371094}}, {"label": "barrel", "coordinates": {"x": 684.0, "y": 670.0, "width": 36.58258056640625, "height": 45.05194091796875}}, {"label": "barrel", "coordinates": {"x": 1387.0, "y": 747.0, "width": 33.658447265625, "height": 44.99456787109375}}, {"label": "barrel", "coordinates": {"x": 900.0, "y": 749.0, "width": 32.46246337890625, "height": 45.63018798828125}}, {"label": "barrel", "coordinates": {"x": 951.0, "y": 350.0, "width": 33.83306884765625, "height": 47.07891845703125}}, {"label": "barrel", "coordinates": {"x": 680.0, "y": 747.0, "width": 31.2318115234375, "height": 43.0855712890625}}, {"label": "barrel", "coordinates": {"x": 198.0, "y": 399.0, "width": 33.168731689453125, "height": 43.24725341796875}}, {"label": "barrel", "coordinates": {"x": 981.0, "y": 750.0, "width": 32.11224365234375, "height": 48.63543701171875}}, {"label": "barrel", "coordinates": {"x": 1487.0, "y": 591.0, "width": 36.8001708984375, "height": 42.8126220703125}}, {"label": "worm", "coordinates": {"x": 1796.7521367521365, "y": 729.1196581196581, "width": 30.0, "height": 32.0}}, {"label": "worm", "coordinates": {"x": 1468.7521367521365, "y": 758.1196581196581, "width": 30.0, "height": 34.0}}, {"label": "worm", "coordinates": {"x": 372.7521367521366, "y": 632.6196581196581, "width": 22.0, "height": 31.0}}, {"label": "mine", "coordinates": {"x": 470.2521367521366, "y": 766.6196581196581, "width": 21.0, "height": 17.0}}, {"label": "mine", "coordinates": {"x": 226.2521367521366, "y": 751.6196581196581, "width": 21.0, "height": 17.0}}, {"label": "mine", "coordinates": {"x": 172.7521367521366, "y": 624.6196581196581, "width": 24.0, "height": 21.0}}, {"label": "mine", "coordinates": {"x": 90.7521367521366, "y": 610.1196581196581, "width": 20.0, "height": 16.0}}, {"label": "mine", "coordinates": {"x": 280.7521367521366, "y": 355.1196581196581, "width": 20.0, "height": 16.0}}, {"label": "mine", "coordinates": {"x": 522.7521367521366, "y": 525.6196581196581, "width": 20.0, "height": 21.0}}, {"label": "mine", "coordinates": {"x": 658.7521367521366, "y": 477.6196581196581, "width": 24.0, "height": 19.0}}, {"label": "mine", "coordinates": {"x": 955.2521367521366, "y": 528.1196581196581, "width": 21.0, "height": 20.0}}, {"label": "mine", "coordinates": {"x": 1009.7521367521366, "y": 277.1196581196581, "width": 20.0, "height": 18.0}}, {"label": "mine", "coordinates": {"x": 1117.2521367521365, "y": 277.1196581196581, "width": 23.0, "height": 18.0}}, {"label": "mine", "coordinates": {"x": 1278.2521367521365, "y": 307.1196581196581, "width": 21.0, "height": 18.0}}, {"label": "mine", "coordinates": {"x": 1414.2521367521365, "y": 354.6196581196581, "width": 21.0, "height": 17.0}}, {"label": "mine", "coordinates": {"x": 1442.2521367521365, "y": 494.6196581196581, "width": 19.0, "height": 17.0}}, {"label": "mine", "coordinates": {"x": 1550.2521367521365, "y": 681.6196581196581, "width": 17.0, "height": 15.0}}, {"label": "mine", "coordinates": {"x": 1684.7521367521365, "y": 320.1196581196581, "width": 16.0, "height": 14.0}}, {"label": "mine", "coordinates": {"x": 766.7521367521366, "y": 696.1196581196581, "width": 16.0, "height": 14.0}}]}]